{"mapCode": "B738643250648B5A52", "mode": "intro", "key": "intro_B738643250648B5A52", "players": {"3": [{"destination": "2, 3", "rules": ["within_fissure", "within_desert", "water_or_bone"], "hint": "hint_not_3"}, {"destination": "5, 3", "rules": ["within_fissure", "within_blue", "water_or_forest"], "hint": "hint_not_2"}, {"destination": "7, 2", "rules": ["within_bone", "water_or_desert", "within_active_fissure"], "hint": "hint_not_3"}, {"destination": "8, 2", "rules": ["within_water", "within_fissure", "within_blue"], "hint": "hint_not_on_on"}, {"destination": "9, 3", "rules": ["within_dormant_fissure", "within_blue", "water_or_forest"], "hint": "hint_not_1"}], "4": [{"destination": "1, 10", "rules": ["within_bone", "forest_or_desert", "within_water", "within_fissure"], "hint": "hint_not_3"}, {"destination": "2, 3", "rules": ["within_fissure", "within_desert", "water_or_forest", "within_red"], "hint": "hint_not_2"}, {"destination": "4, 4", "rules": ["within_blue", "within_active_fissure", "water_or_forest", "within_water"], "hint": "hint_mountain"}, {"destination": "5, 3", "rules": ["within_fissure", "forest_or_desert", "within_red", "within_bone"], "hint": "hint_not_2"}, {"destination": "5, 10", "rules": ["within_bone", "water_or_forest", "within_active_fissure", "within_desert"], "hint": "hint_not_3"}, {"destination": "7, 2", "rules": ["within_green", "water_or_desert", "forest_or_desert", "within_bone"], "hint": "hint_not_2"}, {"destination": "8, 10", "rules": ["within_red", "water_or_desert", "within_green", "within_desert"], "hint": "hint_not_2"}, {"destination": "9, 10", "rules": ["within_red", "forest_or_desert", "within_desert", "within_active_fissure"], "hint": "hint_bone"}], "5": [{"destination": "2, 7", "rules": ["forest_or_desert", "within_dormant_fissure", "forest_or_mountain", "within_bone", "within_fissure"], "hint": "hint_not_3"}, {"destination": "2, 10", "rules": ["water_or_forest", "within_bone", "within_dormant_fissure", "water_or_desert", "within_desert"], "hint": "hint_not_3"}, {"destination": "4, 4", "rules": ["within_water", "forest_or_mountain", "forest_or_bone", "within_bone", "within_active_fissure"], "hint": "hint_not_3"}, {"destination": "4, 6", "rules": ["water_or_mountain", "water_or_bone", "within_red", "within_bone", "within_desert"], "hint": "hint_not_2"}, {"destination": "5, 10", "rules": ["within_fissure", "within_green", "within_bone", "within_desert", "forest_or_bone"], "hint": "hint_not_2"}, {"destination": "6, 8", "rules": ["within_desert", "forest_or_bone", "within_green", "within_blue", "forest_or_mountain"], "hint": "hint_not_2"}, {"destination": "7, 2", "rules": ["within_bone", "within_green", "within_desert", "desert_or_bone", "within_fissure"], "hint": "hint_not_2"}, {"destination": "7, 3", "rules": ["water_or_bone", "within_dormant_fissure", "within_desert", "within_blue", "within_red"], "hint": "hint_mountain"}, {"destination": "7, 6", "rules": ["forest_or_mountain", "within_bone", "within_blue", "forest_or_bone", "within_desert"], "hint": "hint_not_2"}, {"destination": "8, 2", "rules": ["within_green", "within_bone", "within_dormant_fissure", "within_water", "within_fissure"], "hint": "hint_not_on_on"}, {"destination": "8, 3", "rules": ["within_blue", "within_water", "water_or_bone", "mountain_or_bone", "within_desert"], "hint": "hint_not_2"}], "2": [{"destination": "4, 4", "rules": ["within_blue", "within_active_fissure", "water_or_forest", "within_water"], "hint": "hint_bone"}, {"destination": "5, 3", "rules": ["within_fissure", "forest_or_desert", "within_red", "within_bone"], "hint": "hint_not_2"}]}}